foris_plugins_distutils/__init__.py
foris_plugins_distutils-0.31.1.dist-info/METADATA
foris_plugins_distutils-0.31.1.dist-info/WHEEL
foris_plugins_distutils-0.31.1.dist-info/entry_points.txt
foris_plugins_distutils-0.31.1.dist-info/top_level.txt
foris_plugins_distutils-0.31.1.dist-info/RECORD
